pymush/__init__.py
pymush/app.py
pymush/config.py
pymush/conn.py
pymush/game.py
pymush/launcher.py
pymush/selectscreen.py
pymush/welcome.py
pymush-0.0.1.data/scripts/pymush
pymush-0.0.1.dist-info/METADATA
pymush-0.0.1.dist-info/WHEEL
pymush-0.0.1.dist-info/top_level.txt
pymush-0.0.1.dist-info/RECORD
