Metadata-Version: 2.1
Name: pymush
Version: 0.0.1
Summary: UNKNOWN
Home-page: https://github.com/volundmush/pymush
Author: Volund
Maintainer: Volund
License: ???
Project-URL: Source, https://github.com/volundmush/pymush
Project-URL: Issue tracker, https://github.com/volundmush/pymush/issues
Project-URL: Patreon, https://www.patreon.com/volund
Platform: UNKNOWN
Classifier: Programming Language :: Python :: 3 :: Only
Classifier: Programming Language :: Python :: 3.8
Classifier: Intended Audience :: Developers
Classifier: Topic :: Games/Entertainment :: Multi-User Dungeons (MUD)
Classifier: Topic :: Games/Entertainment :: Puzzle Games
Classifier: Topic :: Games/Entertainment :: Role-Playing
Classifier: Topic :: Games/Entertainment :: Simulation
Classifier: Topic :: Software Development :: Libraries :: Application Frameworks
Requires-Python: >=3.8
Requires-Dist: athanor
Requires-Dist: mudstring
Requires-Dist: rich
Requires-Dist: passlib
Requires-Dist: argon2-cffi
Requires-Dist: pytz
Requires-Dist: numpy
Requires-Dist: scipy
